precogs_cli/__init__.py
precogs_cli/config.py
precogs_cli/main.py
precogs_cli-0.1.0.dist-info/METADATA
precogs_cli-0.1.0.dist-info/WHEEL
precogs_cli-0.1.0.dist-info/entry_points.txt
precogs_cli-0.1.0.dist-info/licenses/LICENSE
precogs_cli-0.1.0.dist-info/RECORD
