Metadata-Version: 2.4
Name: precogs-cli
Version: 0.1.0
Summary: Command-line interface for Precogs AI security platform
Project-URL: Homepage, https://precogs.ai
Project-URL: Documentation, https://docs.precogs.ai/cli
Project-URL: Repository, https://github.com/precogsai/precogs-cli
Author-email: Precogs AI <support@precogs.ai>
License-Expression: MIT
License-File: LICENSE
Keywords: cli,code-analysis,devsecops,security,vulnerability
Classifier: Development Status :: 4 - Beta
Classifier: Environment :: Console
Classifier: Intended Audience :: Developers
Classifier: License :: OSI Approved :: MIT License
Classifier: Programming Language :: Python :: 3
Classifier: Programming Language :: Python :: 3.8
Classifier: Programming Language :: Python :: 3.9
Classifier: Programming Language :: Python :: 3.10
Classifier: Programming Language :: Python :: 3.11
Classifier: Programming Language :: Python :: 3.12
Classifier: Topic :: Security
Requires-Python: >=3.8
Requires-Dist: precogs-sdk>=0.1.0
Requires-Dist: rich>=13.0.0
Requires-Dist: typer>=0.9.0
Provides-Extra: dev
Requires-Dist: pytest>=7.0.0; extra == 'dev'
Requires-Dist: ruff>=0.1.0; extra == 'dev'
